Metadata-Version: 2.1
Name: magda
Version: 0.1.0
Summary: Library for building Modular and Asynchronous Graphs with Directed and Acyclic edges (MAGDA)
Home-page: https://github.com/NeuroSYS-pl/magda
Author: NeuroSYS Research
License: Apache 2.0
Keywords: magda modular asynchronous parallelizationdirected-graphs acyclic-graphs pipeline python
Platform: UNKNOWN
Requires-Python: >=3.7
Requires-Dist: pyyaml (<6,>=5.3.1)
Requires-Dist: ray (<2,>=1.2.0)
Provides-Extra: test
Requires-Dist: pytest (==6.1.*) ; extra == 'test'
Requires-Dist: pytest-cov (==2.10.*) ; extra == 'test'
Requires-Dist: pytest-asyncio (==0.14.*) ; extra == 'test'
